{
    "teams": [
        {
            "cover": "/teams/Arsenal.png", 
            "title": "Arsenal"
        }, 
        {
            "cover": "/teams/Aston Villa.png", 
            "title": "Aston Villa"
        },
        {
            "cover": "/teams/Chelsea.png", 
            "title": "Chelsea"
        },
        {
            "cover": "/teams/CrystalPalace.png", 
            "title": "Crystal Palace"
        }, 
        {
            "cover": "/teams/Everton.png", 
            "title": "Everton"
        },
        {
            "cover": "/teams/LeicesterCity.png", 
            "title": "Leicester City"
        },
        {
            "cover": "/teams/Liverpool.png", 
            "title": "Liverpool"
        },
        {
            "cover": "/teams/ManchesterCity.png", 
            "title": "Manchester City"
        },
        {
            "cover": "/teams/ManchesterUnited.png", 
            "title": "Manchester United"
        },
        {
            "cover": "/teams/Newcastle.png", 
            "title": "Newcastle"
        },
        {
            "cover": "/teams/Southampton.png", 
            "title": "Southampton"
        },
        {
            "cover": "/teams/Tottenham.png", 
            "title": "Tottenham"
        }
    ]
}