[
  {
    "Player": "David de Gea",
    "Nation": "es ESP",
    "Pos": "GK",
    "Age": "30",
    "MP": "38",
    "Starts": "38",
    "Min": "3,420",
    "90s": "38",
    "Gls": "0",
    "Ast": "0",
    "G+A": "0",
    "G-PK": "0",
    "PK": "0",
    "PKatt": "0",
    "CrdY": "0",
    "CrdR": "0"
  },
  {
    "Player": "Bruno Fernandes",
    "Nation": "pt POR",
    "Pos": "MF",
    "Age": "26",
    "MP": "36",
    "Starts": "35",
    "Min": "3,111",
    "90s": "34.6",
    "Gls": "10",
    "Ast": "6",
    "G+A": "16",
    "G-PK": "10",
    "PK": "0",
    "PKatt": "2",
    "CrdY": "10",
    "CrdR": "0"
  },
  {
    "Player": "Harry Maguire",
    "Nation": "eng ENG",
    "Pos": "DF",
    "Age": "28",
    "MP": "30",
    "Starts": "28",
    "Min": "2,515",
    "90s": "27.9",
    "Gls": "1",
    "Ast": "0",
    "G+A": "1",
    "G-PK": "1",
    "PK": "0",
    "PKatt": "0",
    "CrdY": "9",
    "CrdR": "1"
  },
  {
    "Player": "Scott McTominay",
    "Nation": "sct SCO",
    "Pos": "MF",
    "Age": "24",
    "MP": "30",
    "Starts": "28",
    "Min": "2,387",
    "90s": "26.5",
    "Gls": "1",
    "Ast": "1",
    "G+A": "2",
    "G-PK": "1",
    "PK": "0",
    "PKatt": "0",
    "CrdY": "9",
    "CrdR": "0"
  },
  {
    "Player": "Cristiano Ronaldo",
    "Nation": "pt POR",
    "Pos": "FW",
    "Age": "36",
    "MP": "30",
    "Starts": "27",
    "Min": "2,456",
    "90s": "27.3",
    "Gls": "18",
    "Ast": "3",
    "G+A": "21",
    "G-PK": "15",
    "PK": "3",
    "PKatt": "3",
    "CrdY": "8",
    "CrdR": "0"
  },
  {
    "Player": "Victor Lindelöf",
    "Nation": "se SWE",
    "Pos": "DF",
    "Age": "27",
    "MP": "28",
    "Starts": "26",
    "Min": "2,355",
    "90s": "26.2",
    "Gls": "0",
    "Ast": "2",
    "G+A": "2",
    "G-PK": "0",
    "PK": "0",
    "PKatt": "0",
    "CrdY": "4",
    "CrdR": "0"
  },
  {
    "Player": "Fred",
    "Nation": "br BRA",
    "Pos": "MF",
    "Age": "28",
    "MP": "28",
    "Starts": "24",
    "Min": "2,028",
    "90s": "22.5",
    "Gls": "4",
    "Ast": "4",
    "G+A": "8",
    "G-PK": "4",
    "PK": "0",
    "PKatt": "0",
    "CrdY": "5",
    "CrdR": "0"
  },
  {
    "Player": "Jadon Sancho",
    "Nation": "eng ENG",
    "Pos": "FW,MF",
    "Age": "21",
    "MP": "29",
    "Starts": "20",
    "Min": "1,900",
    "90s": "21.1",
    "Gls": "3",
    "Ast": "3",
    "G+A": "6",
    "G-PK": "3",
    "PK": "0",
    "PKatt": "0",
    "CrdY": "0",
    "CrdR": "0"
  },
  {
    "Player": "Raphaël Varane",
    "Nation": "fr FRA",
    "Pos": "DF",
    "Age": "28",
    "MP": "22",
    "Starts": "20",
    "Min": "1,831",
    "90s": "20.3",
    "Gls": "1",
    "Ast": "1",
    "G+A": "2",
    "G-PK": "1",
    "PK": "0",
    "PKatt": "0",
    "CrdY": "0",
    "CrdR": "0"
  },
  {
    "Player": "Aaron Wan-Bissaka",
    "Nation": "eng ENG",
    "Pos": "DF",
    "Age": "23",
    "MP": "20",
    "Starts": "20",
    "Min": "1,793",
    "90s": "19.9",
    "Gls": "0",
    "Ast": "0",
    "G+A": "0",
    "G-PK": "0",
    "PK": "0",
    "PKatt": "0",
    "CrdY": "2",
    "CrdR": "0"
  },
  {
    "Player": "Diogo Dalot",
    "Nation": "pt POR",
    "Pos": "DF",
    "Age": "22",
    "MP": "24",
    "Starts": "19",
    "Min": "1,801",
    "90s": "20",
    "Gls": "0",
    "Ast": "0",
    "G+A": "0",
    "G-PK": "0",
    "PK": "0",
    "PKatt": "0",
    "CrdY": "4",
    "CrdR": "0"
  },
  {
    "Player": "Luke Shaw",
    "Nation": "eng ENG",
    "Pos": "DF",
    "Age": "26",
    "MP": "20",
    "Starts": "19",
    "Min": "1,601",
    "90s": "17.8",
    "Gls": "0",
    "Ast": "3",
    "G+A": "3",
    "G-PK": "0",
    "PK": "0",
    "PKatt": "0",
    "CrdY": "8",
    "CrdR": "0"
  },
  {
    "Player": "Alex Telles",
    "Nation": "br BRA",
    "Pos": "DF",
    "Age": "28",
    "MP": "21",
    "Starts": "18",
    "Min": "1,660",
    "90s": "18.4",
    "Gls": "0",
    "Ast": "4",
    "G+A": "4",
    "G-PK": "0",
    "PK": "0",
    "PKatt": "0",
    "CrdY": "1",
    "CrdR": "0"
  },
  {
    "Player": "Nemanja Matić",
    "Nation": "rs SRB",
    "Pos": "MF",
    "Age": "32",
    "MP": "23",
    "Starts": "16",
    "Min": "1,382",
    "90s": "15.4",
    "Gls": "0",
    "Ast": "4",
    "G+A": "4",
    "G-PK": "0",
    "PK": "0",
    "PKatt": "0",
    "CrdY": "3",
    "CrdR": "0"
  },
  {
    "Player": "Paul Pogba",
    "Nation": "fr FRA",
    "Pos": "MF,FW",
    "Age": "28",
    "MP": "20",
    "Starts": "16",
    "Min": "1,349",
    "90s": "15",
    "Gls": "1",
    "Ast": "9",
    "G+A": "10",
    "G-PK": "1",
    "PK": "0",
    "PKatt": "0",
    "CrdY": "7",
    "CrdR": "1"
  },
  {
    "Player": "Mason Greenwood",
    "Nation": "eng ENG",
    "Pos": "FW,MF",
    "Age": "19",
    "MP": "18",
    "Starts": "16",
    "Min": "1,271",
    "90s": "14.1",
    "Gls": "5",
    "Ast": "1",
    "G+A": "6",
    "G-PK": "5",
    "PK": "0",
    "PKatt": "0",
    "CrdY": "1",
    "CrdR": "0"
  },
  {
    "Player": "Anthony Elanga",
    "Nation": "se SWE",
    "Pos": "FW",
    "Age": "19",
    "MP": "21",
    "Starts": "14",
    "Min": "1,214",
    "90s": "13.5",
    "Gls": "2",
    "Ast": "2",
    "G+A": "4",
    "G-PK": "2",
    "PK": "0",
    "PKatt": "0",
    "CrdY": "0",
    "CrdR": "0"
  },
  {
    "Player": "Marcus Rashford",
    "Nation": "eng ENG",
    "Pos": "FW,MF",
    "Age": "23",
    "MP": "25",
    "Starts": "13",
    "Min": "1,235",
    "90s": "13.7",
    "Gls": "4",
    "Ast": "2",
    "G+A": "6",
    "G-PK": "4",
    "PK": "0",
    "PKatt": "0",
    "CrdY": "2",
    "CrdR": "0"
  },
  {
    "Player": "Edinson Cavani",
    "Nation": "uy URU",
    "Pos": "FW",
    "Age": "34",
    "MP": "15",
    "Starts": "7",
    "Min": "766",
    "90s": "8.5",
    "Gls": "2",
    "Ast": "1",
    "G+A": "3",
    "G-PK": "2",
    "PK": "0",
    "PKatt": "0",
    "CrdY": "0",
    "CrdR": "0"
  },
  {
    "Player": "Eric Bailly",
    "Nation": "ci CIV",
    "Pos": "DF",
    "Age": "27",
    "MP": "4",
    "Starts": "3",
    "Min": "217",
    "90s": "2.4",
    "Gls": "0",
    "Ast": "0",
    "G+A": "0",
    "G-PK": "0",
    "PK": "0",
    "PKatt": "0",
    "CrdY": "1",
    "CrdR": "0"
  },
  {
    "Player": "Jesse Lingard",
    "Nation": "eng ENG",
    "Pos": "FW,MF",
    "Age": "28",
    "MP": "16",
    "Starts": "2",
    "Min": "367",
    "90s": "4.1",
    "Gls": "2",
    "Ast": "0",
    "G+A": "2",
    "G-PK": "2",
    "PK": "0",
    "PKatt": "0",
    "CrdY": "1",
    "CrdR": "0"
  }
]