[
  {
    "Player": "David de Gea",
    "Nation": "es ESP",
    "Pos": "GK",
    "Age": "31",
    "MP": "38",
    "Starts": "38",
    "Min": "3,420",
    "90s": "38",
    "Gls": "0",
    "Ast": "0",
    "G+A": "0",
    "G-PK": "0",
    "PK": "0",
    "PKatt": "0",
    "CrdY": "0",
    "CrdR": "0"
  },
  {
    "Player": "Bruno Fernandes",
    "Nation": "pt POR",
    "Pos": "MF,FW",
    "Age": "27",
    "MP": "37",
    "Starts": "37",
    "Min": "3,316",
    "90s": "36.8",
    "Gls": "8",
    "Ast": "8",
    "G+A": "16",
    "G-PK": "6",
    "PK": "2",
    "PKatt": "2",
    "CrdY": "6",
    "CrdR": "0"
  },
  {
    "Player": "Marcus Rashford",
    "Nation": "eng ENG",
    "Pos": "FW",
    "Age": "24",
    "MP": "35",
    "Starts": "32",
    "Min": "2,879",
    "90s": "32",
    "Gls": "17",
    "Ast": "5",
    "G+A": "22",
    "G-PK": "17",
    "PK": "0",
    "PKatt": "0",
    "CrdY": "2",
    "CrdR": "0"
  },
  {
    "Player": "Luke Shaw",
    "Nation": "eng ENG",
    "Pos": "DF",
    "Age": "27",
    "MP": "31",
    "Starts": "30",
    "Min": "2,552",
    "90s": "28.4",
    "Gls": "1",
    "Ast": "2",
    "G+A": "3",
    "G-PK": "1",
    "PK": "0",
    "PKatt": "0",
    "CrdY": "8",
    "CrdR": "0"
  },
  {
    "Player": "Christian Eriksen",
    "Nation": "dk DEN",
    "Pos": "MF",
    "Age": "30",
    "MP": "28",
    "Starts": "25",
    "Min": "2,048",
    "90s": "22.8",
    "Gls": "1",
    "Ast": "8",
    "G+A": "9",
    "G-PK": "1",
    "PK": "0",
    "PKatt": "0",
    "CrdY": "3",
    "CrdR": "0"
  },
  {
    "Player": "Diogo Dalot",
    "Nation": "pt POR",
    "Pos": "DF",
    "Age": "23",
    "MP": "26",
    "Starts": "24",
    "Min": "2,154",
    "90s": "23.9",
    "Gls": "1",
    "Ast": "2",
    "G+A": "3",
    "G-PK": "1",
    "PK": "0",
    "PKatt": "0",
    "CrdY": "6",
    "CrdR": "0"
  },
  {
    "Player": "Casemiro",
    "Nation": "br BRA",
    "Pos": "MF",
    "Age": "30",
    "MP": "28",
    "Starts": "24",
    "Min": "2,124",
    "90s": "23.6",
    "Gls": "4",
    "Ast": "3",
    "G+A": "7",
    "G-PK": "4",
    "PK": "0",
    "PKatt": "0",
    "CrdY": "7",
    "CrdR": "2"
  },
  {
    "Player": "Lisandro Martínez",
    "Nation": "ar ARG",
    "Pos": "DF",
    "Age": "24",
    "MP": "27",
    "Starts": "24",
    "Min": "2,114",
    "90s": "23.5",
    "Gls": "1",
    "Ast": "0",
    "G+A": "1",
    "G-PK": "1",
    "PK": "0",
    "PKatt": "0",
    "CrdY": "6",
    "CrdR": "0"
  },
  {
    "Player": "Antony",
    "Nation": "br BRA",
    "Pos": "FW",
    "Age": "22",
    "MP": "25",
    "Starts": "23",
    "Min": "1,802",
    "90s": "20",
    "Gls": "4",
    "Ast": "2",
    "G+A": "6",
    "G-PK": "4",
    "PK": "0",
    "PKatt": "0",
    "CrdY": "5",
    "CrdR": "0"
  },
  {
    "Player": "Raphaël Varane",
    "Nation": "fr FRA",
    "Pos": "DF",
    "Age": "29",
    "MP": "24",
    "Starts": "22",
    "Min": "1,911",
    "90s": "21.2",
    "Gls": "0",
    "Ast": "0",
    "G+A": "0",
    "G-PK": "0",
    "PK": "0",
    "PKatt": "0",
    "CrdY": "1",
    "CrdR": "0"
  },
  {
    "Player": "Jadon Sancho",
    "Nation": "eng ENG",
    "Pos": "FW,MF",
    "Age": "22",
    "MP": "26",
    "Starts": "21",
    "Min": "1,686",
    "90s": "18.7",
    "Gls": "6",
    "Ast": "3",
    "G+A": "9",
    "G-PK": "6",
    "PK": "0",
    "PKatt": "0",
    "CrdY": "0",
    "CrdR": "0"
  },
  {
    "Player": "Aaron Wan-Bissaka",
    "Nation": "eng ENG",
    "Pos": "DF",
    "Age": "24",
    "MP": "19",
    "Starts": "16",
    "Min": "1,435",
    "90s": "15.9",
    "Gls": "0",
    "Ast": "0",
    "G+A": "0",
    "G-PK": "0",
    "PK": "0",
    "PKatt": "0",
    "CrdY": "2",
    "CrdR": "0"
  },
  {
    "Player": "Tyrell Malacia",
    "Nation": "nl NED",
    "Pos": "DF",
    "Age": "22",
    "MP": "22",
    "Starts": "14",
    "Min": "1,396",
    "90s": "15.5",
    "Gls": "0",
    "Ast": "0",
    "G+A": "0",
    "G-PK": "0",
    "PK": "0",
    "PKatt": "0",
    "CrdY": "6",
    "CrdR": "0"
  },
  {
    "Player": "Victor Lindelöf",
    "Nation": "se SWE",
    "Pos": "DF",
    "Age": "28",
    "MP": "20",
    "Starts": "14",
    "Min": "1,365",
    "90s": "15.2",
    "Gls": "0",
    "Ast": "0",
    "G+A": "0",
    "G-PK": "0",
    "PK": "0",
    "PKatt": "0",
    "CrdY": "1",
    "CrdR": "0"
  },
  {
    "Player": "Fred",
    "Nation": "br BRA",
    "Pos": "MF",
    "Age": "29",
    "MP": "35",
    "Starts": "12",
    "Min": "1,249",
    "90s": "13.9",
    "Gls": "2",
    "Ast": "2",
    "G+A": "4",
    "G-PK": "2",
    "PK": "0",
    "PKatt": "0",
    "CrdY": "6",
    "CrdR": "0"
  },
  {
    "Player": "Anthony Martial",
    "Nation": "fr FRA",
    "Pos": "FW",
    "Age": "26",
    "MP": "21",
    "Starts": "11",
    "Min": "978",
    "90s": "10.9",
    "Gls": "6",
    "Ast": "2",
    "G+A": "8",
    "G-PK": "5",
    "PK": "1",
    "PKatt": "1",
    "CrdY": "0",
    "CrdR": "0"
  },
  {
    "Player": "Scott McTominay",
    "Nation": "sct SCO",
    "Pos": "MF",
    "Age": "25",
    "MP": "24",
    "Starts": "10",
    "Min": "1,160",
    "90s": "12.9",
    "Gls": "1",
    "Ast": "0",
    "G+A": "1",
    "G-PK": "1",
    "PK": "0",
    "PKatt": "0",
    "CrdY": "8",
    "CrdR": "0"
  },
  {
    "Player": "Wout Weghorst",
    "Nation": "nl NED",
    "Pos": "FW,MF",
    "Age": "29",
    "MP": "17",
    "Starts": "10",
    "Min": "797",
    "90s": "8.9",
    "Gls": "0",
    "Ast": "1",
    "G+A": "1",
    "G-PK": "0",
    "PK": "0",
    "PKatt": "0",
    "CrdY": "1",
    "CrdR": "0"
  },
  {
    "Player": "Harry Maguire",
    "Nation": "eng ENG",
    "Pos": "DF",
    "Age": "29",
    "MP": "16",
    "Starts": "8",
    "Min": "767",
    "90s": "8.5",
    "Gls": "0",
    "Ast": "0",
    "G+A": "0",
    "G-PK": "0",
    "PK": "0",
    "PKatt": "0",
    "CrdY": "4",
    "CrdR": "0"
  },
  {
    "Player": "Marcel Sabitzer",
    "Nation": "at AUT",
    "Pos": "MF",
    "Age": "28",
    "MP": "11",
    "Starts": "7",
    "Min": "627",
    "90s": "7",
    "Gls": "0",
    "Ast": "1",
    "G+A": "1",
    "G-PK": "0",
    "PK": "0",
    "PKatt": "0",
    "CrdY": "1",
    "CrdR": "0"
  }
]